Metadata-Version: 2.1
Name: odoo14-addon-user_log_view
Version: 14.0.1.0.1.dev5
Summary: Allow to see user's actions log
Home-page: https://github.com/OCA/server-auth
Author: IT-Projects LLC, Odoo Community Association (OCA)
Author-email: support@odoo-community.org
License: LGPL-3
Classifier: Programming Language :: Python
Classifier: Framework :: Odoo
Classifier: Framework :: Odoo :: 14.0
Classifier: License :: OSI Approved :: GNU Lesser General Public License v3 (LGPLv3)
Classifier: Development Status :: 5 - Production/Stable
Requires-Python: >=3.6
Requires-Dist: odoo<14.1dev,>=14.0a
